{"path":"api/CsvHelper.Configuration.Attributes/DateTimeStylesAttribute","templateID":1,"sharedPropsHashes":{"toc":"Z6psdd"},"localProps":{"className":"/DateTimeStylesAttribute","data":"# DateTimeStylesAttribute Class\r\n\r\nNamespace: [CsvHelper.Configuration.Attributes](/api/CsvHelper.Configuration.Attributes)\r\n\r\nThe ``CsvHelper.Configuration.Attributes.DateTimeStylesAttribute.DateTimeStyles`` to use when type converting. This is used when doing any ``System.DateTime`` conversions.\r\n\r\n```cs\r\n[System.AttributeUsageAttribute]\r\npublic class DateTimeStylesAttribute : Attribute\r\n```\r\n\r\nInheritance Object -> Attribute -> DateTimeStylesAttribute\r\n\r\n## Constructors\r\n&nbsp; | &nbsp;\r\n- | -\r\nDateTimeStylesAttribute(DateTimeStyles) | The ``CsvHelper.Configuration.Attributes.DateTimeStylesAttribute.DateTimeStyles`` to use when type converting. This is used when doing any ``System.DateTime`` conversions.\r\n\r\n## Properties\r\n&nbsp; | &nbsp;\r\n- | -\r\nDateTimeStyles | Gets the date time styles.\r\n"}}
